files_to_prompt/__init__.py
files_to_prompt/__main__.py
files_to_prompt/cli.py
files_to_prompt-0.4.dist-info/LICENSE
files_to_prompt-0.4.dist-info/METADATA
files_to_prompt-0.4.dist-info/WHEEL
files_to_prompt-0.4.dist-info/entry_points.txt
files_to_prompt-0.4.dist-info/top_level.txt
files_to_prompt-0.4.dist-info/RECORD
