Metadata-Version: 2.1
Name: files-to-prompt
Version: 0.4
Summary: Concatenate a directory full of files into a single prompt for use with LLMs
Author: Simon Willison
License: Apache-2.0
Project-URL: Homepage, https://github.com/simonw/files-to-prompt
Project-URL: Changelog, https://github.com/simonw/files-to-prompt/releases
Project-URL: Issues, https://github.com/simonw/files-to-prompt/issues
Project-URL: CI, https://github.com/simonw/files-to-prompt/actions
Classifier: License :: OSI Approved :: Apache Software License
Requires-Python: >=3.8
License-File: LICENSE
Requires-Dist: click
Provides-Extra: test
Requires-Dist: pytest ; extra == 'test'
